lss_parser/__init__.py
lss_parser/models.py
lss_parser/parser.py
lss_parser/serializer.py
lss_parser/utils.py
lss_parser-0.1.0.dist-info/METADATA
lss_parser-0.1.0.dist-info/WHEEL
lss_parser-0.1.0.dist-info/RECORD
