Metadata-Version: 2.4
Name: lss-parser
Version: 0.1.0
Summary: A Python module for parsing and manipulating LiveSplit .lss files
Project-URL: Homepage, https://github.com/mushroomsuprise/lss-parser
Project-URL: Bug Reports, https://github.com/mushroomsuprise/lss-parser/issues
Project-URL: Source, https://github.com/mushroomsuprise/lss-parser
Author: mushroomsuprise
License: MIT
Keywords: livesplit,lss,parser,speedrunning,xml
Classifier: Development Status :: 4 - Beta
Classifier: Intended Audience :: Developers
Classifier: License :: OSI Approved :: MIT License
Classifier: Programming Language :: Python :: 3
Classifier: Programming Language :: Python :: 3.8
Classifier: Programming Language :: Python :: 3.9
Classifier: Programming Language :: Python :: 3.10
Classifier: Programming Language :: Python :: 3.11
Classifier: Programming Language :: Python :: 3.12
Classifier: Programming Language :: Python :: 3.13
Classifier: Topic :: Games/Entertainment
Classifier: Topic :: Software Development :: Libraries :: Python Modules
Requires-Python: >=3.8
Requires-Dist: pydantic>=2.0.0
